quickbeutils/__init__.py
quickbeutils/aws_ses.py
quickbeutils/gmail.py
quickbeutils/helpers.py
quickbeutils/slack.py
quickbeutils-1.2.3.dist-info/METADATA
quickbeutils-1.2.3.dist-info/WHEEL
quickbeutils-1.2.3.dist-info/top_level.txt
quickbeutils-1.2.3.dist-info/RECORD
