Metadata-Version: 2.1
Name: quickbeutils
Version: 1.2.3
Summary: All sorts of utilities
Home-page: https://github.com/eldad1221/quickbelog
Author: Eldad Bishari
Author-email: eldad@1221tlv.org
Classifier: Programming Language :: Python :: 3
Classifier: License :: OSI Approved :: MIT License
Classifier: Operating System :: OS Independent
Requires-Python: >=3.7
Requires-Dist: requests >=2.27.1
Requires-Dist: quickbelog >=1.1.0
